README.rst
setup.cfg
setup.py
sceleton/__init__.py
sceleton/cli.py
sceleton/command.py
sceleton.egg-info/PKG-INFO
sceleton.egg-info/SOURCES.txt
sceleton.egg-info/dependency_links.txt
sceleton.egg-info/entry_points.txt
sceleton.egg-info/requires.txt
sceleton.egg-info/top_level.txt
sceleton.egg-info/zip-safe
sceleton/commands/__init__.py
sceleton/commands/add.py
sceleton/commands/build.py
sceleton/commands/classifiers.py
sceleton/commands/init.py
sceleton/commands/install.py
sceleton/commands/keywords.py
sceleton/commands/license.py
sceleton/commands/local.py
sceleton/commands/module.py
sceleton/commands/new.py
sceleton/commands/remove.py
sceleton/commands/sdist.py
sceleton/commands/upload.py
sceleton/commands/user.py
sceleton/commands/venv.py
sceleton/decorators/__init__.py
sceleton/decorators/missing_file.py
sceleton/decorators/subargs.py
sceleton/structure/__init__.py
sceleton/structure/project/__init__.py
sceleton/structure/project/classifier.py
sceleton/structure/project/git.py
sceleton/structure/project/license.py
sceleton/structure/project/package.py
sceleton/structure/project/project.py
sceleton/structure/project/readme.py
sceleton/structure/project/setup_py.py
sceleton/structure/project/venv.py
sceleton/structure/project/licenses/Academic Free License (AFL).txt
sceleton/structure/project/licenses/Aladdin Free Public License (AFPL).txt
sceleton/structure/project/licenses/Apache Software License.txt
sceleton/structure/project/licenses/Apple Public Source License.txt
sceleton/structure/project/licenses/Artistic License.txt
sceleton/structure/project/licenses/Attribution Assurance License.txt
sceleton/structure/project/licenses/BSD License.txt
sceleton/structure/project/licenses/Boost Software License 1.0 (BSL-1.0).txt
sceleton/structure/project/licenses/CC0 1.0 Universal (CC0 1.0) Public Domain Dedication.txt
sceleton/structure/project/licenses/CEA CNRS Inria Logiciel Libre License, version 2.1 (CeCILL-2.1).txt
sceleton/structure/project/licenses/COMMON DEVELOPMENT AND DISTRIBUTION LICENSE (CDDL).txt
sceleton/structure/project/licenses/CeCILL-B Free Software License Agreement (CECILL-B).txt
