Metadata-Version: 1.1
Name: sceleton
Version: 0.0.5
Summary: CLI tool for creating packages in python3.
Home-page: https://github.com/monzita/sceleton
Author: Monika Ilieva
Author-email: email@example.com
License: MIT License
Keywords: python3 sceleton package manager
Platform: UNKNOWN
Classifier: Development Status :: 3 - Alpha
Classifier: Environment :: Console
Classifier: Programming Language :: Python :: 3.7
Classifier: Programming Language :: Python :: 3.8
Classifier: Programming Language :: Python :: 3 :: Only
Classifier: Topic :: Utilities
Classifier: License :: OSI Approved :: MIT License
